lambda_deploy/__init__.py
lambda_deploy/__main__.py
lambda_deploy/lambda_deploy.py
lambda_deploy/utils.py
lambda_deploy/version.py
lambda_deploy-0.1.2.dist-info/DESCRIPTION.rst
lambda_deploy-0.1.2.dist-info/METADATA
lambda_deploy-0.1.2.dist-info/RECORD
lambda_deploy-0.1.2.dist-info/WHEEL
lambda_deploy-0.1.2.dist-info/entry_points.txt
lambda_deploy-0.1.2.dist-info/metadata.json
lambda_deploy-0.1.2.dist-info/top_level.txt
