Metadata-Version: 2.0
Name: lambda-deploy
Version: 0.1.2
Summary: Easily deploy code to AWS Lambda
Home-page: https://github.com/jimjkelly/lambda-deploy
Author: James Kelly
Author-email: pthread1981@gmail.com
License: MIT
Keywords: aws lambda
Platform: UNKNOWN
Classifier: Development Status :: 4 - Beta
Classifier: License :: OSI Approved :: MIT License
Classifier: Intended Audience :: Developers
Classifier: Environment :: Console
Classifier: Programming Language :: Python
Classifier: Natural Language :: English
Classifier: Programming Language :: Python :: 2
Classifier: Programming Language :: Python :: 2.7
Classifier: Topic :: System :: Software Distribution
Requires-Dist: boto3 (>=1.3.0)
Requires-Dist: requests (>=2.9.1)
Requires-Dist: yaep (>=0.0.4)
